{
    "data": {
        "message": [
            {
                "name": "John",
                "phone_no": "+48100100",
                "email": "john@a.pl",
                "shifts": [
                    "[Thu] Oct 08, 10 AM",
                    "[Sat] Oct 10, 09 AM"
                ],
                "shifts_no_format": [
                    "2023-03-08 10:00",
                    "2023-03-10 09:00"
                ]
            },
            {
                "name": "Mark",
                "phone_no": "+48200200",
                "email": "mark@a.pl",
                "shifts": [
                    "[Sat] Oct 10, 11 AM"
                ],
                "shifts_no_format": [
                    "2023-03-09 09:00"
                ]
            }
        ],
        "caller": "schedule_manager",
        "flow": "SEND_TO_RECIPIENTS"
    }
}